<launch4jConfig>
  <dontWrapJar>true</dontWrapJar>
  <headerType>gui</headerType>
  <jar>WildLog.jar</jar>
  <outfile>C:\Users\Henry\Documents\NetBeansProjects\WildLog\StableReleases\Installer Config Files\WildLog\WildLog.exe</outfile>
  <errTitle>WildLog Startup Error</errTitle>
  <cmdLine>log_to_file</cmdLine>
  <chdir></chdir>
  <priority>normal</priority>
  <downloadUrl>http://java.com/download</downloadUrl>
  <supportUrl>http://www.mywild.co.za</supportUrl>
  <customProcName>true</customProcName>
  <stayAlive>false</stayAlive>
  <manifest></manifest>
  <icon>C:\Users\Henry\Documents\NetBeansProjects\WildLog\StableReleases\Installer Config Files\WildLog\WildLog.ico</icon>
  <jre>
    <path></path>
    <minVersion>1.7.0</minVersion>
    <maxVersion></maxVersion>
    <jdkPreference>preferJre</jdkPreference>
    <opt>-Xms128m</opt>
  </jre>
  <versionInfo>
    <fileVersion>4.0.0.0</fileVersion>
    <txtFileVersion>WildLog v4.0 Launcher</txtFileVersion>
    <fileDescription>WildLog Application: EXE wrapper for WildLog.jar</fileDescription>
    <copyright>2013</copyright>
    <productVersion>4.0.0.0</productVersion>
    <txtProductVersion>WildLog v4.0 Launcher</txtProductVersion>
    <productName>WildLog</productName>
    <companyName>MyWild</companyName>
    <internalName>WildLog</internalName>
    <originalFilename>WildLog.exe</originalFilename>
  </versionInfo>
</launch4jConfig>