<?xml version="1.0" encoding="UTF-8"?>
<launch4jConfig>
  <dontWrapJar>true</dontWrapJar>
  <headerType>gui</headerType>
  <jar>.\WildLog-WEIVolunteer.jar</jar>
  <outfile>C:\_Code\GitHub\WildLog\WildLog\StableReleases\Installer Config Files\WildLog\application\WildLog-WEIVolunteer.exe</outfile>
  <errTitle>WildLog Startup Error</errTitle>
  <cmdLine>properties=./wildlog.properties</cmdLine>
  <chdir></chdir>
  <priority>normal</priority>
  <downloadUrl>http://java.com/download</downloadUrl>
  <supportUrl>http://www.mywild.co.za</supportUrl>
  <stayAlive>false</stayAlive>
  <restartOnCrash>false</restartOnCrash>
  <manifest></manifest>
  <icon>C:\_Code\GitHub\WildLog\WildLog\StableReleases\Installer Config Files\misc files\WEI-Volunteer.ico</icon>
  <jre>
    <path>jre_1_8_0_212</path>
    <bundledJre64Bit>false</bundledJre64Bit>
    <bundledJreAsFallback>false</bundledJreAsFallback>
    <minVersion>1.8.0</minVersion>
    <maxVersion></maxVersion>
    <jdkPreference>preferJre</jdkPreference>
    <runtimeBits>64/32</runtimeBits>
    <initialHeapSize>512</initialHeapSize>
    <maxHeapSize>1024</maxHeapSize>
    <maxHeapPercent>80</maxHeapPercent>
  </jre>
  <splash>
    <file>C:\_Code\GitHub\WildLog\WildLog\StableReleases\Installer Config Files\misc files\LaunchScreen.bmp</file>
    <waitForWindow>true</waitForWindow>
    <timeout>600</timeout>
    <timeoutErr>true</timeoutErr>
  </splash>
  <versionInfo>
    <fileVersion>6.0.0.0</fileVersion>
    <txtFileVersion>WildLog v6.0.0 Launcher</txtFileVersion>
    <fileDescription>WildLog Application: EXE wrapper for WildLog.jar</fileDescription>
    <copyright>2019</copyright>
    <productVersion>6.0.0.0</productVersion>
    <txtProductVersion>WildLog v6.0.0</txtProductVersion>
    <productName>WildLog</productName>
    <companyName>MyWild</companyName>
    <internalName>WildLog</internalName>
    <originalFilename>WildLog.exe</originalFilename>
    <trademarks></trademarks>
    <language>ENGLISH_US</language>
  </versionInfo>
</launch4jConfig>